README.txt
setup.py
trac_UserPicturesPlugin.egg-info/PKG-INFO
trac_UserPicturesPlugin.egg-info/SOURCES.txt
trac_UserPicturesPlugin.egg-info/dependency_links.txt
trac_UserPicturesPlugin.egg-info/entry_points.txt
trac_UserPicturesPlugin.egg-info/not-zip-safe
trac_UserPicturesPlugin.egg-info/top_level.txt
userpictures/__init__.py
userpictures/providers/__init__.py
userpictures/providers/gravatar.py
userpictures/providers/usermanager.py