Metadata-Version: 1.0
Name: trac-UserPicturesPlugin
Version: 0.1
Summary: Adds user pictures to Trac
Home-page: http://trac-hacks.org/wiki/UserPicturesPlugin
Author: Ethan Jucovy
Author-email: ejucovy@gmail.com
License: BSD
Keywords: trac plugin
Platform: UNKNOWN
